<?xml version="1.0" encoding="UTF-8"?>
<!DOCTYPE suite SYSTEM "https://testng.org/testng-1.0.dtd">
<suite name="Suite">
  <test thread-count="5" name="Test">
    <classes>
      <class name="beautyProducts.TC_BeautyProducts_014"/>
      <class name="shoppingcCart.TC_ShoppingCart_023"/>
      <class name="shoppingcCart.TC_ShoppingCart_022"/>
      <class name="shoppingcCart.TC_ShoppingCart_021"/>
      <class name="shoppingcCart.TC_ShoppingCart_020"/>
      <class name="beautyProducts.TC_BeautyProducts_012"/>
      <class name="beautyProducts.TC_BeautyProducts_013"/>
      <class name="beautyProducts.TC_BeautyProducts_011"/>
    </classes>
  </test> <!-- Test -->
</suite> <!-- Suite -->
